<annotation>
	<folder></folder>
	<filename>download--5-_jpg.rf.adcb24e53d8d1fd8bdbce8fbc33f5e1d.jpg</filename>
	<path>download--5-_jpg.rf.adcb24e53d8d1fd8bdbce8fbc33f5e1d.jpg</path>
	<source>
		<database>roboflow.ai</database>
	</source>
	<size>
		<width>416</width>
		<height>416</height>
		<depth>3</depth>
	</size>
	<segmented>0</segmented>
	<object>
		<name>foul</name>
		<pose>Unspecified</pose>
		<truncated>0</truncated>
		<difficult>0</difficult>
		<occluded>0</occluded>
		<bndbox>
			<xmin>66</xmin>
			<xmax>152</xmax>
			<ymin>98</ymin>
			<ymax>415</ymax>
		</bndbox>
	</object>
</annotation>
